minfraud/__init__.py
minfraud/errors.py
minfraud/models.py
minfraud/py.typed
minfraud/request.py
minfraud/validation.py
minfraud/version.py
minfraud/webservice.py
minfraud-3.1.0.dist-info/licenses/LICENSE
minfraud-3.1.0.dist-info/METADATA
minfraud-3.1.0.dist-info/WHEEL
minfraud-3.1.0.dist-info/top_level.txt
minfraud-3.1.0.dist-info/RECORD
