Metadata-Version: 2.4
Name: minfraud
Version: 3.1.0
Summary: MaxMind minFraud API
Author-email: Gregory Oschwald <goschwald@maxmind.com>
License-Expression: Apache-2.0
Project-URL: Homepage, https://www.maxmind.com/
Project-URL: Documentation, https://minfraud.readthedocs.org/
Project-URL: Source Code, https://github.com/maxmind/minfraud-api-python
Project-URL: Issue Tracker, https://github.com/maxmind/minfraud-api-python/issues
Classifier: Development Status :: 5 - Production/Stable
Classifier: Environment :: Web Environment
Classifier: Intended Audience :: Developers
Classifier: Programming Language :: Python
Classifier: Programming Language :: Python :: 3
Classifier: Programming Language :: Python :: 3.9
Classifier: Programming Language :: Python :: 3.10
Classifier: Programming Language :: Python :: 3.11
Classifier: Programming Language :: Python :: 3.12
Classifier: Programming Language :: Python :: 3.13
Classifier: Topic :: Internet
Classifier: Topic :: Internet :: Proxy Servers
Classifier: Topic :: Internet :: WWW/HTTP
Requires-Python: >=3.9
License-File: LICENSE
Requires-Dist: aiohttp<4.0.0,>=3.6.2
Requires-Dist: email_validator<3.0.0,>=2.0.0
Requires-Dist: geoip2<6.0.0,>=5.1.0
Requires-Dist: requests<3.0.0,>=2.24.0
Requires-Dist: typing-extensions>=4.13.2
Requires-Dist: voluptuous
Dynamic: license-file
